Metadata-Version: 1.2
Name: distributions-study
Version: 1.6
Summary: Gaussian and Binomial distributions
Home-page: UNKNOWN
Author: Shivtej Shete
Author-email: shivtej.shete@gmail.com
License: MIT
Platform: UNKNOWN
Classifier: Programming Language :: Python :: 3
Classifier: License :: OSI Approved :: MIT License
Requires-Python: >=3.6.3
